mc_status_webhook.py
mc_status_webhook-0.4.0.dist-info/LICENSE
mc_status_webhook-0.4.0.dist-info/METADATA
mc_status_webhook-0.4.0.dist-info/WHEEL
mc_status_webhook-0.4.0.dist-info/entry_points.txt
mc_status_webhook-0.4.0.dist-info/top_level.txt
mc_status_webhook-0.4.0.dist-info/RECORD
