Metadata-Version: 2.1
Name: mc-status-webhook
Version: 0.4.0
Summary: Minecraft server status webhook for Discord
Home-page: https://github.com/alexitx/mc-status-webhook
Author: alexitx
Author-email: alexander@alexitx.com
License: MIT
Project-URL: Bug Tracker, https://github.com/alexitx/mc-status-webhook/issues
Project-URL: Source, https://github.com/alexitx/mc-status-webhook
Keywords: minecraft,server,discord,webhook,status,ping,monitoring,logging
Platform: UNKNOWN
Classifier: Development Status :: 4 - Beta
Classifier: Intended Audience :: Developers
Classifier: Intended Audience :: End Users/Desktop
Classifier: Intended Audience :: System Administrators
Classifier: License :: OSI Approved :: MIT License
Classifier: Natural Language :: English
Classifier: Operating System :: Microsoft :: Windows
Classifier: Operating System :: OS Independent
Classifier: Operating System :: POSIX :: Linux
Classifier: Operating System :: Unix
Classifier: Programming Language :: Python :: 3
Classifier: Programming Language :: Python :: 3 :: Only
Classifier: Programming Language :: Python :: 3.7
Classifier: Programming Language :: Python :: 3.8
Classifier: Programming Language :: Python :: 3.9
Classifier: Programming Language :: Python :: 3.10
Classifier: Programming Language :: Python :: Implementation :: CPython
Classifier: Topic :: Internet :: WWW/HTTP
Classifier: Topic :: System :: Logging
Classifier: Topic :: System :: Monitoring
Classifier: Topic :: System :: Networking :: Monitoring
Classifier: Topic :: Utilities
Requires-Python: >=3.7
License-File: LICENSE
Requires-Dist: discord-webhook (~=0.15)
Requires-Dist: mcstatus (~=8.0)
